generic/__init__.py
generic/bucket.py
generic/ccloud_lib.py
generic/query.py
sbf_generic_functions/__init__.py
sbf_generic_functions/bucket.py
sbf_generic_functions/ccloud_lib.py
sbf_generic_functions/query.py
datalibsbf-0.6.dist-info/METADATA
datalibsbf-0.6.dist-info/WHEEL
datalibsbf-0.6.dist-info/top_level.txt
datalibsbf-0.6.dist-info/RECORD
