Metadata-Version: 2.1
Name: datalibsbf
Version: 0.6
Summary: Lib de disponibilizacao de funcoes genericas criadas dentro do time de dados
Home-page: https://github.com/grupo-sbf/data-libs
Author: Matheus Beltrão
Author-email: matheus.beltrao@gruposbf.com.br
License: UNKNOWN
Platform: UNKNOWN
Requires-Dist: awswrangler
Requires-Dist: google-cloud-bigquery
Requires-Dist: redshift-connector
Requires-Dist: pandas
Requires-Dist: cx-Oracle
Requires-Dist: pyodbc
Requires-Dist: boto3
